{
    "category": "Search",
    "description": "Use an online service to find the address for a point on the map.",
    "ignore": false,
    "images": [
        "ReverseGeocodeOnline.png"
    ],
    "keywords": [
        "address",
        "geocode",
        "locate",
        "reverse geocode",
        "search",
        "GeocodeParameters",
        "LocatorTask",
        "ReverseGeocodeParameters"
    ],
    "redirect_from": [
        "/java/latest/sample-code/reverse-geocode-online.htm"
    ],
    "relevant_apis": [
        "GeocodeParameters",
        "LocatorTask",
        "ReverseGeocodeParameters"
    ],
    "snippets": [
        "src/main/java/com/esri/samples/reverse_geocode_online/ReverseGeocodeOnlineSample.java"
    ],
    "title": "Reverse geocode online"
}
