{
    "category": "Editing",
    "description": "@@TODO: Delete features from an online feature service.",
    "ignore": false,
    "images": [],
    "keywords": [
        "@@TODO: *** PLEASE ADD ADDITIONAL KEYWORDS ***",
        "ArcGISMap",
        "Feature",
        "FeatureLayer",
        "MapView",
        "ServiceFeatureTable"
    ],
    "redirect_from": "/java/latest/sample-code/delete-features.htm",
    "relevant_apis": [
        "ArcGISMap",
        "Feature",
        "FeatureLayer",
        "MapView",
        "ServiceFeatureTable"
    ],
    "snippets": [
        "@@TODO: *** PLEASE VERIFY THE INCLUSION OF THESE SNIPPETS ***",
        "DeleteFeaturesSample.java"
    ],
    "title": "@@TODO: Delete Features"
}
