{
    "category": "Map",
    "description": "@@TODO: Determine when a map has finished loading.",
    "ignore": false,
    "images": [
        "AccessLoadStatus.png"
    ],
    "keywords": [
        "@@TODO: *** PLEASE ADD ADDITIONAL KEYWORDS ***",
        "ArcGISMap",
        "Basemap",
        "MapView",
        "LoadStatus"
    ],
    "redirect_from": "/java/latest/sample-code/access-load-status.htm",
    "relevant_apis": [
        "ArcGISMap",
        "Basemap",
        "MapView",
        "LoadStatus"
    ],
    "snippets": [
        "@@TODO: *** PLEASE VERIFY THE INCLUSION OF THESE SNIPPETS ***",
        "src/main/java/com/esri/samples/access_load_status/AccessLoadStatusSample.java",
        "src/main/java/com/esri/samples/access_load_status/AccessLoadStatusLauncher.java"
    ],
    "title": "@@TODO: Access Load Status"
}
